LICENSE
MANIFEST.in
README.md
setup.py
myecho/__init__.py
myecho/__version__.py
myecho/core.py
myecho.egg-info/PKG-INFO
myecho.egg-info/SOURCES.txt
myecho.egg-info/dependency_links.txt
myecho.egg-info/entry_points.txt
myecho.egg-info/top_level.txt